<PAMDataset>
  <PAMRasterBand band="1">
    <Metadata>
      <MDI key="STATISTICS_APPROXIMATE">YES</MDI>
      <MDI key="STATISTICS_MAXIMUM">247</MDI>
      <MDI key="STATISTICS_MEAN">121.68398319626</MDI>
      <MDI key="STATISTICS_MINIMUM">9</MDI>
      <MDI key="STATISTICS_STDDEV">68.018258369674</MDI>
      <MDI key="STATISTICS_VALID_PERCENT">26.23</MDI>
    </Metadata>
  </PAMRasterBand>
  <PAMRasterBand band="2">
    <Metadata>
      <MDI key="STATISTICS_APPROXIMATE">YES</MDI>
      <MDI key="STATISTICS_MAXIMUM">251</MDI>
      <MDI key="STATISTICS_MEAN">172.42192769659</MDI>
      <MDI key="STATISTICS_MINIMUM">49</MDI>
      <MDI key="STATISTICS_STDDEV">45.659892288277</MDI>
      <MDI key="STATISTICS_VALID_PERCENT">26.23</MDI>
    </Metadata>
  </PAMRasterBand>
  <PAMRasterBand band="3">
    <Metadata>
      <MDI key="STATISTICS_APPROXIMATE">YES</MDI>
      <MDI key="STATISTICS_MAXIMUM">255</MDI>
      <MDI key="STATISTICS_MEAN">212.00798769304</MDI>
      <MDI key="STATISTICS_MINIMUM">108</MDI>
      <MDI key="STATISTICS_STDDEV">27.922854667317</MDI>
      <MDI key="STATISTICS_VALID_PERCENT">26.23</MDI>
    </Metadata>
  </PAMRasterBand>
</PAMDataset>
